LICENSE
cpm-0.8.1.dev71.dist-info/DESCRIPTION.rst
cpm-0.8.1.dev71.dist-info/METADATA
cpm-0.8.1.dev71.dist-info/RECORD
cpm-0.8.1.dev71.dist-info/WHEEL
cpm-0.8.1.dev71.dist-info/metadata.json
cpm-0.8.1.dev71.dist-info/top_level.txt
crosspm/__init__.py
crosspm/__main__.py
crosspm/cmakepm.cmake
crosspm/cpm.py
crosspm/pm_arti_download.py
crosspm/pm_pack.py
crosspm/pm_promote_deps.py
crosspm/adapters/__init__.py
crosspm/adapters/artifactory.py
crosspm/adapters/common.py
crosspm/helpers/__init__.py
crosspm/helpers/archive.py
crosspm/helpers/config.py
crosspm/helpers/downloader.py
crosspm/helpers/exceptions.py
crosspm/helpers/output.py
crosspm/helpers/package.py
crosspm/helpers/parser.py
crosspm/helpers/promoter.py
crosspm/helpers/source.py
