Metadata-Version: 2.0
Name: cpm
Version: 0.8.1.dev71
Summary: Cross Package Manager
Home-page: https://github.com/devopshq/crosspm.git
Author: Alexander Kovalev
Author-email: ak@alkov.pro
License: MIT
Keywords: development,dependency,requirements
Platform: UNKNOWN
Classifier: Development Status :: 4 - Beta
Classifier: Intended Audience :: Developers
Classifier: Topic :: Software Development :: Build Tools
Classifier: License :: OSI Approved :: MIT License
Classifier: Programming Language :: Python :: 3
Classifier: Programming Language :: Python :: 3.1
Classifier: Programming Language :: Python :: 3.2
Classifier: Programming Language :: Python :: 3.3
Classifier: Programming Language :: Python :: 3.4
Classifier: Programming Language :: Python :: 3.5
Requires-Dist: docopt
Requires-Dist: dohq-art
Requires-Dist: pyyaml
Requires-Dist: requests
